prime_sieve/__init__.py
prime_sieve/array.py
prime_sieve/base.py
prime_sieve/list.py
prime_sieve/math_utils.py
prime_sieve-0.1.11.dist-info/AUTHORS.rst
prime_sieve-0.1.11.dist-info/LICENSE
prime_sieve-0.1.11.dist-info/METADATA
prime_sieve-0.1.11.dist-info/WHEEL
prime_sieve-0.1.11.dist-info/top_level.txt
prime_sieve-0.1.11.dist-info/RECORD
