Metadata-Version: 1.2
Name: prime-sieve
Version: 0.1.11
Summary: An understandable prime sieve implementation in numpy or pure python.
Home-page: https://github.com/mCodingLLC/prime_sieve
Author: James Murphy
Author-email: james@mcoding.io
License: MIT license
Keywords: prime_sieve
Platform: UNKNOWN
Classifier: Development Status :: 2 - Pre-Alpha
Classifier: Intended Audience :: Developers
Classifier: License :: OSI Approved :: MIT License
Classifier: Natural Language :: English
Classifier: Programming Language :: Python :: 3
Classifier: Programming Language :: Python :: 3.6
Classifier: Programming Language :: Python :: 3.7
Classifier: Programming Language :: Python :: 3.8
Classifier: Programming Language :: Python :: 3.9
Requires-Python: >=3.6
